pybrastr/__init__.py
pybrastr/str.py
pybrastr-0.1.2.dist-info/LICENSE
pybrastr-0.1.2.dist-info/METADATA
pybrastr-0.1.2.dist-info/WHEEL
pybrastr-0.1.2.dist-info/RECORD
