Metadata-Version: 2.1
Name: pybrastr
Version: 0.1.2
Summary: Brainstorming package to manage string
License: MIT
Author: Brainstorming
Author-email: Support.erp@brainstorming.eu
Requires-Python: >=3.10,<4.0
Classifier: License :: OSI Approved :: MIT License
Classifier: Programming Language :: Python :: 3
Classifier: Programming Language :: Python :: 3.10
Classifier: Programming Language :: Python :: 3.11
Classifier: Programming Language :: Python :: 3.12
